casper/__init__.py
casper/casper.py
py_casper-1.1.0.dist-info/LICENSE
py_casper-1.1.0.dist-info/METADATA
py_casper-1.1.0.dist-info/WHEEL
py_casper-1.1.0.dist-info/top_level.txt
py_casper-1.1.0.dist-info/RECORD
