Metadata-Version: 2.1
Name: py-casper
Version: 1.1.0
Summary: A python package to predict halo concentration and shape parameter.
Home-page: https://github.com/Shaun-T-Brown/CASPER
Author: Shaun Brown
Author-email: s.t.brown@2018.ljmu.ac.uk
License: UNKNOWN
Platform: UNKNOWN
Classifier: Programming Language :: Python :: 3
Classifier: License :: OSI Approved :: MIT License
Classifier: Operating System :: OS Independent
Requires-Python: >=3.6
License-File: LICENSE
Requires-Dist: numpy
Requires-Dist: scipy
